py_trading/__init__.py
py_trading/base.py
py_trading/download_tickers.py
py_trading/live_trading.py
py_trading/stock_info.py
py_trading/tempCodeRunnerFile.py
pythontrading/__init__.py
pythontrading/base.py
pythontrading/download_tickers.py
pythontrading/live_trading.py
pythontrading/stock_info.py
Py_Trading-0.4.9.11.dist-info/LICENSE
Py_Trading-0.4.9.11.dist-info/METADATA
Py_Trading-0.4.9.11.dist-info/WHEEL
Py_Trading-0.4.9.11.dist-info/top_level.txt
Py_Trading-0.4.9.11.dist-info/RECORD
