Metadata-Version: 2.1
Name: Py-Trading
Version: 0.4.9.11
Summary: A Python module for trading information.
Home-page: https://github.com/JCamyre/Python-Trading
Author: Joseph Camyre
Author-email: jwcamry03@gmail.com
Classifier: Programming Language :: Python :: 3
Classifier: License :: OSI Approved :: MIT License
Classifier: Operating System :: OS Independent
Requires-Python: >=3.6
License-File: LICENSE
Requires-Dist: asgiref (==3.3.2)
Requires-Dist: beautifulsoup4 (==4.9.3)
Requires-Dist: certifi (==2020.12.5)
Requires-Dist: cffi (==1.14.4)
Requires-Dist: chardet (==4.0.0)
Requires-Dist: click (==7.1.2)
Requires-Dist: cryptography (==3.4.2)
Requires-Dist: cycler (==0.10.0)
Requires-Dist: et-xmlfile (==1.0.1)
Requires-Dist: Flask (==1.1.2)
Requires-Dist: GoogleNews (==1.5.5)
Requires-Dist: html5lib (==1.1)
Requires-Dist: idna (==2.10)
Requires-Dist: itsdangerous (==1.1.0)
Requires-Dist: jdcal (==1.4.1)
Requires-Dist: Jinja2 (==2.11.3)
Requires-Dist: kiwisolver (==1.3.1)
Requires-Dist: lxml (>=4.6.3)
Requires-Dist: MarkupSafe (==1.1.1)
Requires-Dist: matplotlib (==3.3.3)
Requires-Dist: mplfinance (==0.12.7a5)
Requires-Dist: numpy (==1.20.3)
Requires-Dist: oauthlib (==3.1.0)
Requires-Dist: openpyxl (==3.0.6)
Requires-Dist: pandas (==1.2.1)
Requires-Dist: Pillow (>=8.2.0)
Requires-Dist: pycparser (==2.20)
Requires-Dist: pyOpenSSL (==20.0.1)
Requires-Dist: pyparsing (==2.4.7)
Requires-Dist: python-dateutil (==2.8.1)
Requires-Dist: python-dotenv (==0.15.0)
Requires-Dist: pytz (==2020.5)
Requires-Dist: requests (==2.25.1)
Requires-Dist: requests-oauthlib (==1.3.0)
Requires-Dist: six (==1.15.0)
Requires-Dist: td-ameritrade-python-api (==0.3.4)
Requires-Dist: tweepy (==3.10.0)
Requires-Dist: urllib3 (>=1.26.5)
Requires-Dist: websockets (>=9.1)
Requires-Dist: Werkzeug (==1.0.1)
